miniautogen/__init__.py
miniautogen/agent/__init__.py
miniautogen/agent/agent.py
miniautogen/chat/__init__.py
miniautogen/chat/chat.py
miniautogen/chat/chatadmin.py
miniautogen/llms/__init__.py
miniautogen/llms/llm_client.py
miniautogen/pipeline/__init__.py
miniautogen/pipeline/components/__init__.py
miniautogen/pipeline/components/components.py
miniautogen/pipeline/components/pipelinecomponent.py
miniautogen/pipeline/pipeline.py
miniautogen/storage/__init__.py
miniautogen/storage/chatstorage.py
miniautogen-0.0.1.dist-info/METADATA
miniautogen-0.0.1.dist-info/WHEEL
miniautogen-0.0.1.dist-info/RECORD
