Metadata-Version: 2.1
Name: miniautogen
Version: 0.0.1
Summary: Lightweight and flexible library for creating multi-agent agents and conversations.
License: MIT
Author: Bruno Capelão
Author-email: brcapelao@gmail.com
Requires-Python: >3.10,<3.12
Classifier: License :: OSI Approved :: MIT License
Classifier: Programming Language :: Python :: 3
Classifier: Programming Language :: Python :: 3.11
Requires-Dist: litellm (==1.16.12)
Requires-Dist: openai (==1.3.9)
Requires-Dist: pandas (==2.1.4)
Requires-Dist: python-dotenv (==1.0.0)
Requires-Dist: sqlalchemy (==2.0.23)
